{"nodes": [{"id": "src_server_map_food_js", "label": "food.js", "file_type": "code", "source_file": "src\\server\\map\\food.js", "source_location": "L1"}, {"id": "food_food", "label": "Food", "file_type": "code", "source_file": "src\\server\\map\\food.js", "source_location": "L7"}, {"id": "food_food_constructor", "label": ".constructor()", "file_type": "code", "source_file": "src\\server\\map\\food.js", "source_location": "L8"}, {"id": "food_constructor", "label": "constructor()", "file_type": "code", "source_file": "src\\server\\map\\food.js", "source_location": "L19"}, {"id": "food_addnew", "label": "addNew()", "file_type": "code", "source_file": "src\\server\\map\\food.js", "source_location": "L25"}, {"id": "food_removeexcess", "label": "removeExcess()", "file_type": "code", "source_file": "src\\server\\map\\food.js", "source_location": "L33"}, {"id": "food_delete", "label": "delete()", "file_type": "code", "source_file": "src\\server\\map\\food.js", "source_location": "L39"}], "edges": [{"source": "src_server_map_food_js", "target": "food_food", "relation": "contains", "confidence": "EXTRACTED", "source_file": "src\\server\\map\\food.js", "source_location": "L7", "weight": 1.0}, {"source": "food_food", "target": "food_food_constructor", "relation": "method", "confidence": "EXTRACTED", "source_file": "src\\server\\map\\food.js", "source_location": "L8", "weight": 1.0}, {"source": "src_server_map_food_js", "target": "food_constructor", "relation": "contains", "confidence": "EXTRACTED", "source_file": "src\\server\\map\\food.js", "source_location": "L19", "weight": 1.0}, {"source": "src_server_map_food_js", "target": "food_addnew", "relation": "contains", "confidence": "EXTRACTED", "source_file": "src\\server\\map\\food.js", "source_location": "L25", "weight": 1.0}, {"source": "src_server_map_food_js", "target": "food_removeexcess", "relation": "contains", "confidence": "EXTRACTED", "source_file": "src\\server\\map\\food.js", "source_location": "L33", "weight": 1.0}, {"source": "src_server_map_food_js", "target": "food_delete", "relation": "contains", "confidence": "EXTRACTED", "source_file": "src\\server\\map\\food.js", "source_location": "L39", "weight": 1.0}], "raw_calls": [{"caller_nid": "food_food_constructor", "callee": "uuidv4", "source_file": "src\\server\\map\\food.js", "source_location": "L9"}, {"caller_nid": "food_food_constructor", "callee": "random", "source_file": "src\\server\\map\\food.js", "source_location": "L13"}, {"caller_nid": "food_food_constructor", "callee": "round", "source_file": "src\\server\\map\\food.js", "source_location": "L14"}, {"caller_nid": "food_food_constructor", "callee": "random", "source_file": "src\\server\\map\\food.js", "source_location": "L14"}, {"caller_nid": "food_addnew", "callee": "massToRadius", "source_file": "src\\server\\map\\food.js", "source_location": "L26"}, {"caller_nid": "food_addnew", "callee": "getPosition", "source_file": "src\\server\\map\\food.js", "source_location": "L28"}, {"caller_nid": "food_addnew", "callee": "push", "source_file": "src\\server\\map\\food.js", "source_location": "L29"}, {"caller_nid": "food_removeexcess", "callee": "pop", "source_file": "src\\server\\map\\food.js", "source_location": "L35"}, {"caller_nid": "food_delete", "callee": "removeIndexes", "source_file": "src\\server\\map\\food.js", "source_location": "L41"}]}